umlts_folioapi/__init__.py
umlts_folioapi/folioApi.py
umlts_folioapi/config/config.example.ini
umlts_folioapi-0.0.6.dist-info/METADATA
umlts_folioapi-0.0.6.dist-info/WHEEL
umlts_folioapi-0.0.6.dist-info/licenses/LICENSE
umlts_folioapi-0.0.6.dist-info/RECORD
